Metadata-Version: 2.1
Name: securedrop-log
Version: 0.0.3
Summary: SecureDrop Qubes logging scripts
Home-page: https://github.com/freedomofpress/securedrop-log
Author: Freedom of the Press Foundation
Author-email: securedrop@freedom.press
License: GPLv3+
Platform: UNKNOWN
Classifier: Development Status :: 3 - Alpha
Classifier: Programming Language :: Python :: 3
Classifier: Topic :: Software Development :: Libraries :: Python Modules
Classifier: License :: OSI Approved :: GNU General Public License v3 or later (GPLv3+)
Classifier: Intended Audience :: Developers
Classifier: Operating System :: POSIX :: Linux
Requires-Python: >=3.5
